corn/conf.py
corn/scripts.py
corn/version.py
corn/corn/init.py
corn/corn/contracts/init.py
corn-8.dist-info/METADATA
corn-8.dist-info/WHEEL
corn-8.dist-info/entry_points.txt
corn-8.dist-info/top_level.txt
corn-8.dist-info/RECORD
