Metadata-Version: 2.1
Name: corn
Version: 8
Summary: System information discovery and asset tracking
Home-page: https://gitlab.com/saltstack/pop/corn
Author: 
Author-email: 
License: UNKNOWN
Platform: UNKNOWN
Classifier: Operating System :: OS Independent
Classifier: Programming Language :: Python
Classifier: Programming Language :: Python :: 3.6
Classifier: Programming Language :: Python :: 3.7
Classifier: Programming Language :: Python :: 3.8
Classifier: Development Status :: 5 - Production/Stable
Requires-Python: >=3.6
Requires-Dist: pop (>=13)
Requires-Dist: pop-config (>=6.2)
Requires-Dist: rend (>=4.2)
